{
  "updated": "2026-04-02T00:04:00",
  "stocks": {
    "600150": {
      "best_strategy": "MA交叉(8/20)",
      "win_rate": 100.0,
      "avg_return": 3.69,
      "score": 2.03,
      "all_top5": [
        "MA交叉(8/20)",
        "MA交叉(8/15)",
        "MA交叉(10/20)",
        "MA交叉(10/15)",
        "MA交叉(5/20)"
      ],
      "ma_fast": 8,
      "ma_slow": 20,
      "prev_best": "MA交叉(8/20)",
      "prev_score": 2.03,
      "change_note": "无显著变化，MA交叉(8/20)维持榜首，胜率100%"
    },
    "600482": {
      "best_strategy": "布林(15,2.0)",
      "win_rate": 50.0,
      "avg_return": 0.59,
      "score": 0.19,
      "all_top5": [
        "布林(15,2.0)",
        "RSI(7,25/75)",
        "RSI(7,30/70)",
        "布林(20,2.0)",
        "布林(25,2.0)"
      ],
      "bb_period": 15,
      "bb_mult": 2.0,
      "prev_best": "布林(15,2.0)",
      "change_note": "无显著变化，Top5策略排名基本一致"
    }
  }
}
